now.py
now_info_cli-1.3.1.dist-info/LICENSE.md
now_info_cli-1.3.1.dist-info/METADATA
now_info_cli-1.3.1.dist-info/WHEEL
now_info_cli-1.3.1.dist-info/entry_points.txt
now_info_cli-1.3.1.dist-info/top_level.txt
now_info_cli-1.3.1.dist-info/RECORD
