Metadata-Version: 2.1
Name: now-info-cli
Version: 1.3.1
Summary: Command line utilities for information about now
Home-page: https://github.com/mr-strawberry66/now-cli
License: UNKNOWN
Platform: UNKNOWN
Requires-Dist: click (==8.0.3)
Requires-Dist: colorama (==0.4.4)
Requires-Dist: requests (==2.27.1)
